{"status": "completed", "result": "failed", "grader_agent": "human", "id": 503052, "user_id": 131701, "notes": null, "repo_url": null, "created_at": "2017-05-18T11:22:58.949Z", "updated_at": "2017-05-22T17:09:07.088Z", "commit_sha": null, "grader_id": 397, "assigned_at": "2017-05-22T15:40:30.740Z", "price": "8.0", "completed_at": "2017-05-22T17:09:07.078Z", "archive_url": "https://udacity-reviews-uploads.s3.amazonaws.com/_submissions/zipfile/503052/newsdata.zip", "zipfile": {"url": "https://udacity-reviews-uploads.s3.amazonaws.com/_submissions/zipfile/503052/newsdata.zip"}, "udacity_key": null, "held_at": null, "status_reason": null, "result_reason": null, "type": null, "training_id": null, "files": [], "url": null, "annotation_urls": [], "general_comment": "Hello!  Your answers to the first section are correct, and it will take only a few minor changes for you to get the right answers in the other two sections.  I've given you some information as to what needs to be done, and a few pages of documentation to refer to if need be.\n\nGreat work so far, you are almost done!", "hidden": false, "previous_submission_id": null, "nomination": null, "language": "en-us", "rubric_id": 277, "is_training": false, "canary_metadata": null, "checkmate_metadata": null, "escalated_at": null, "ungradeable_tag": null, "project_id": 195, "user": {"name": "Adam", "udacity_key": "3843018937"}, "grader": {"name": "Jim", "udacity_key": "736449029"}, "project": {"id": 195, "name": "Logs Analysis"}, "rubric": {"description": "The database for this project can be found [here](https://d17h27t6h515a5.cloudfront.net/topher/2016/August/57b5f748_newsdata/newsdata.zip).\n\nThe student will build a reporting tool in Python to answer several questions and provide the information in a README file.\n\nStudent instructions:\n\nOnce you've completed the project, submit it for review.\n\n[Take a look at the project rubric here.](https://review.udacity.com/#!/rubrics/277/view) These are the code standards that your reviewer will be using to evaluate your code.\n\nYour submission should include:\n\n* **Your program's source code.** Usually this will be one source code file.\n* **An example of your program's output.** This will be a plain text file that is a copy of what your program printed out.\n* **A README.md file** This is a Markdown text file in which you describe the design of your code and how to run it. If you created any views in the database, make sure to put the create view commands into the README file. For more information on writing good READMEs, see [this course](https://classroom.udacity.com/courses/ud777).\n\nYou do not need to include the database, the newsdata.sql file, or any other files besides these.\n", "nomination_eligible": false}}